README.md
setup.cfg
setup.py
para_impute.egg-info/PKG-INFO
para_impute.egg-info/SOURCES.txt
para_impute.egg-info/dependency_links.txt
para_impute.egg-info/requires.txt
para_impute.egg-info/top_level.txt
pimpute/__init__.py
pimpute/RF/__init__.py
pimpute/RF/_imp.py
pimpute/RF/_rf.py
pimpute/RF/consts.py
pimpute/RF/imputer.py
pimpute/RF/hpc/__init__.py
pimpute/RF/hpc/job.py
pimpute/RF/hpc/job_handler.py