Metadata-Version: 2.1
Name: para-impute
Version: 1.0.0
Summary: Missing value imputation package for high-performance computing
Home-page: https://github.com/fangzhouli/para-impute
Author: Fangzhou Li
Author-email: fzli0805@gmail.com
License: MIT
Keywords: impute,imputation,missing data,missing value,missing value imputation,random forest,HPC,high-performance computing,computer cluster,SLURM
Platform: UNKNOWN
Classifier: Development Status :: 3 - Alpha
Classifier: Intended Audience :: Developers
Classifier: Topic :: Software Development :: Build Tools
Classifier: License :: OSI Approved :: MIT License
Classifier: Programming Language :: Python :: 3
